stickler/__init__.py
stickler/algorithms/__init__.py
stickler/algorithms/hungarian.py
stickler/comparators/__init__.py
stickler/comparators/base.py
stickler/comparators/bert.py
stickler/comparators/exact.py
stickler/comparators/fuzzy.py
stickler/comparators/levenshtein.py
stickler/comparators/llm.py
stickler/comparators/numeric.py
stickler/comparators/semantic.py
stickler/comparators/structured.py
stickler/comparators/utils.py
stickler/reporting/html/__init__.py
stickler/reporting/html/html_reporter.py
stickler/reporting/html/report_config.py
stickler/reporting/html/section_generator.py
stickler/reporting/html/visualization_engine.py
stickler/reporting/html/utils/__init__.py
stickler/reporting/html/utils/color_utils.py
stickler/reporting/html/utils/data_extractors.py
stickler/structured_object_evaluator/__init__.py
stickler/structured_object_evaluator/bulk_structured_model_evaluator.py
stickler/structured_object_evaluator/utils.py
stickler/structured_object_evaluator/models/__init__.py
stickler/structured_object_evaluator/models/aggregate_metrics_calculator.py
stickler/structured_object_evaluator/models/comparable_field.py
stickler/structured_object_evaluator/models/comparator_registry.py
stickler/structured_object_evaluator/models/comparison_dispatcher.py
stickler/structured_object_evaluator/models/comparison_engine.py
stickler/structured_object_evaluator/models/comparison_helper.py
stickler/structured_object_evaluator/models/comparison_helper_base.py
stickler/structured_object_evaluator/models/comparison_info.py
stickler/structured_object_evaluator/models/configuration_helper.py
stickler/structured_object_evaluator/models/confusion_matrix_builder.py
stickler/structured_object_evaluator/models/confusion_matrix_calculator.py
stickler/structured_object_evaluator/models/derived_metrics_calculator.py
stickler/structured_object_evaluator/models/evaluator_format_helper.py
stickler/structured_object_evaluator/models/field.py
stickler_eval-0.1.4.dist-info/licenses/LICENSE
stickler_eval-0.1.4.dist-info/licenses/NOTICE
stickler_eval-0.1.4.dist-info/METADATA
stickler_eval-0.1.4.dist-info/WHEEL
stickler_eval-0.1.4.dist-info/top_level.txt
stickler_eval-0.1.4.dist-info/RECORD
