Metadata-Version: 2.4
Name: stickler-eval
Version: 0.1.4
Summary: Structured object comparison and evaluation library
Author-email: Spencer Romo <sromo@amazon.com>, Ayushi Haria <ayuharia@amazon.com>, Aditya Addepalli <adiadd@amazon.com>, Ryan Razkenari <razken@amazon.com>
Requires-Python: >=3.12
License-File: LICENSE
License-File: NOTICE
Requires-Dist: pydantic>=2.11.0
Requires-Dist: rapidfuzz>=3.0.0
Requires-Dist: munkres>=1.1.4
Requires-Dist: numpy>=1.24.0
Requires-Dist: scipy>=1.10.0
Requires-Dist: psutil>=5.8.0
Requires-Dist: pandas>=1.5.0
Requires-Dist: jsonschema>=4.0.0
Provides-Extra: dev
Requires-Dist: pytest>=7.0.0; extra == "dev"
Requires-Dist: pytest-xdist>=3.0.0; extra == "dev"
Requires-Dist: coverage>=7.0.0; extra == "dev"
Requires-Dist: beautifulsoup4>=4.14.2; extra == "dev"
Dynamic: license-file
